{"cameraMode":{"drawMode":0,"name":"Shaded","section":"Shading Mode"},"sceneLighting":true,"audioPlay":false,"sceneViewState":{"showFog":true,"showMaterialUpdate":false,"showSkybox":true,"showFlares":true,"showImageEffects":true,"showParticleSystems":true},"in2DMode":false,"pivot":{"x":23.366056442260743,"y":-21.834131240844728,"z":48.46592330932617},"rotation":{"x":-0.1939559429883957,"y":-0.17205508053302766,"z":0.03457169607281685,"w":-0.9651939272880554},"size":35.69535446166992,"orthographic":false}